__init__.py
main.py
easypaste-1.dist-info/METADATA
easypaste-1.dist-info/WHEEL
easypaste-1.dist-info/licenses/LICENSE
easypaste-1.dist-info/RECORD
